{
  "av52gfs9lRfqtJxVAAAD": {
    "username": "🐴",
    "real": "console 1",
    "punti": 0,
    "prove": 0,
    "classe": "BOL1312",
    "livello": 0
  },
  "rCuQoSPzL7kmViK8AAAF": {
    "username": "🐵",
    "real": "Gabriele Bell&#232;",
    "punti": 30,
    "prove": 10,
    "classe": "BOL1312",
    "livello": 15,
    "voto4": 20
  },
  "TEvPvIFsJ4WthOQiAAAH": {
    "username": "🐶",
    "real": "Mattia Bolamperti",
    "punti": 34,
    "prove": 6,
    "classe": "BOL1312",
    "livello": 16,
    "voto4": 28
  },
  "VP7ATr1lj31T__qNAAAJ": {
    "username": "🐷",
    "real": "Gabriele Petruzzi",
    "punti": 30,
    "prove": 9,
    "classe": "BOL1312",
    "livello": 15,
    "voto4": 21
  },
  "tJ5qxZAIMsUDFrW4AAAL": {
    "username": "🐸",
    "real": "Lorenzo Bucciarell",
    "punti": 21,
    "prove": 7,
    "classe": "BOL1312",
    "livello": 12,
    "voto4": 14
  },
  "UoDkRkRmqpLTygGXAAAN": {
    "username": "🐹",
    "real": "Marco Caruso",
    "punti": 24,
    "prove": 2,
    "classe": "BOL1312",
    "livello": 13,
    "voto4": 22
  },
  "7Hr1MFaZS6bnMc5LAAAP": {
    "username": "🐺",
    "real": "Filippo Martelli",
    "punti": 30,
    "prove": 3,
    "classe": "BOL1312",
    "livello": 15,
    "voto4": 27
  },
  "PQWrWgLFWL5Bv-4DAAAR": {
    "username": "🐻",
    "real": "Luca Simonelli",
    "punti": 27,
    "prove": 2,
    "classe": "BOL1312",
    "livello": 14,
    "voto4": 25
  },
  "mJIuM4myhYNRQJ-3AAAT": {
    "username": "🐼",
    "real": "Maimouna Diop",
    "punti": 21,
    "prove": 7,
    "classe": "BOL1312",
    "livello": 12,
    "voto4": 14
  },
  "324_qGbcjRuEzVlpAAAV": {
    "username": "🐽",
    "real": "Giulio Imeri",
    "punti": 34,
    "prove": 5,
    "classe": "BOL1312",
    "livello": 16,
    "voto4": 29
  },
  "bIyfKb-tZkBjg-OlAAAX": {
    "username": "🐾",
    "real": "Daniel Giordano",
    "punti": 3,
    "prove": 5,
    "classe": "BOL1312",
    "livello": 3,
    "voto4": -2
  },
  "AyKOkiGbbtMhQ4EsAAAZ": {
    "username": "🐿",
    "real": "Christian Fontana",
    "punti": 24,
    "prove": 4,
    "classe": "BOL1312",
    "livello": 13,
    "voto4": 20
  },
  "7OEDBcWyorSkXF7eAAAb": {
    "username": "👀",
    "real": "Tommaso Fridegotto",
    "punti": 13,
    "prove": 4,
    "classe": "BOL1312",
    "livello": 9,
    "voto4": 9
  },
  "pNjrJeYdY0BVepDcAAAd": {
    "username": "👁",
    "real": "Alessandro Trinca",
    "punti": 38,
    "prove": 8,
    "classe": "BOL1312",
    "livello": 17,
    "voto4": 30
  },
  "VJpaG2YJvLUjclhIAAAf": {
    "username": "👂",
    "real": "Alex Piva",
    "punti": 30,
    "prove": 2,
    "classe": "BOL1312",
    "livello": 15,
    "voto4": 28
  }
}